janssqlitekernel/__init__.py
janssqlitekernel/__main__.py
janssqlitekernel/install_kernelspec.py
janssqlitekernel/kernel.py
janssqlitekernel-1.2.0.dist-info/LICENSE
janssqlitekernel-1.2.0.dist-info/METADATA
janssqlitekernel-1.2.0.dist-info/WHEEL
janssqlitekernel-1.2.0.dist-info/entry_points.txt
janssqlitekernel-1.2.0.dist-info/top_level.txt
janssqlitekernel-1.2.0.dist-info/RECORD
