Metadata-Version: 2.1
Name: janssqlitekernel
Version: 1.2.0
Summary: A jupyter SQLite3 kernel.
Author-email: Jan Arman Parpin <is@hidden.com>
Project-URL: Homepage, https://github.com/jans-code/janssqlitekernel
Project-URL: Bug Tracker, https://github.com/jans-code/janssqlitekernel/issues
Classifier: Programming Language :: Python :: 3
Classifier: License :: OSI Approved :: MIT License
Classifier: Operating System :: POSIX :: Linux
Classifier: Framework :: Jupyter :: JupyterLab :: 3
Requires-Python: >=3.7
License-File: LICENSE
Requires-Dist: ipykernel
Requires-Dist: pexpect
